{
  "metadata": {
    "description": "3 additional Grinsztajn clf_num benchmark datasets (eye_movements, credit, miniboone)",
    "source": "inria-soda/tabular-benchmark (HuggingFace)",
    "benchmark": "Grinsztajn et al. 2022 - Why do tree-based models still outperform deep learning on tabular data?",
    "n_datasets": 3,
    "total_examples": 97320
  },
  "datasets": [
    {
      "dataset": "eye_movements",
      "examples": [
        {
          "input": "{\"lineNo\":9684.0,\"assgNo\":298.0,\"prevFixDur\":99.0,\"firstfixDur\":119.0,\"firstPassFixDur\":119.0,\"nextFixDur\":238.0,\"firstSaccLen\":300.1666,\"lastSaccLen\":288.0156,\"prevFixPos\":246.0732,\"landingPos\":56.6326,\"leavingPos\":51.1786,\"totalFixDur\":119.0,\"meanFixDur\":119.0,\"regressLen\":0.0,\"regressDur\":0.0,\"pupilDiamMax\":0.1541,\"pupilDiamLag\":0.4446,\"timePrtctg\":0.0176,\"titleNo\":4.0,\"wordNo\":3.0}",
          "output": "0",
          "metadata_fold": 2,
          "metadata_feature_names": [
            "lineNo",
            "assgNo",
            "prevFixDur",
            "firstfixDur",
            "firstPassFixDur",
            "nextFixDur",
            "firstSaccLen",
            "lastSaccLen",
            "prevFixPos",
            "landingPos",
            "leavingPos",
            "totalFixDur",
            "meanFixDur",
            "regressLen",
            "regressDur",
            "pupilDiamMax",
            "pupilDiamLag",
            "timePrtctg",
            "titleNo",
            "wordNo"
          ],
          "metadata_task_type": "binary_classification",
          "metadata_n_classes": 2,
          "metadata_source": "hf_inria-soda/tabular-benchmark_clf_num_eye_movements",
          "metadata_row_index": 0
        },
        {
          "input": "{\"lineNo\":2065.0,\"assgNo\":66.0,\"prevFixDur\":119.0,\"firstfixDur\":159.0,\"firstPassFixDur\":239.0,\"nextFixDur\":100.0,\"firstSaccLen\":306.1066,\"lastSaccLen\":117.2359,\"prevFixPos\":321.014,\"landingPos\":47.3207,\"leavingPos\":47.0425,\"totalFixDur\":239.0,\"meanFixDur\":119.5,\"regressLen\":0.0,\"regressDur\":159.0,\"pupilDiamMax\":0.0119,\"pupilDiamLag\":0.3264,\"timePrtctg\":0.0239,\"titleNo\":8.0,\"wordNo\":1.0}",
          "output": "0",
          "metadata_fold": 0,
          "metadata_feature_names": [
            "lineNo",
            "assgNo",
            "prevFixDur",
            "firstfixDur",
            "firstPassFixDur",
            "nextFixDur",
            "firstSaccLen",
            "lastSaccLen",
            "prevFixPos",
            "landingPos",
            "leavingPos",
            "totalFixDur",
            "meanFixDur",
            "regressLen",
            "regressDur",
            "pupilDiamMax",
            "pupilDiamLag",
            "timePrtctg",
            "titleNo",
            "wordNo"
          ],
          "metadata_task_type": "binary_classification",
          "metadata_n_classes": 2,
          "metadata_source": "hf_inria-soda/tabular-benchmark_clf_num_eye_movements",
          "metadata_row_index": 1
        },
        {
          "input": "{\"lineNo\":1969.0,\"assgNo\":61.0,\"prevFixDur\":139.0,\"firstfixDur\":139.0,\"firstPassFixDur\":357.0,\"nextFixDur\":179.0,\"firstSaccLen\":590.5294,\"lastSaccLen\":805.0531,\"prevFixPos\":479.3078,\"landingPos\":112.361,\"leavingPos\":118.6529,\"totalFixDur\":536.0,\"meanFixDur\":178.6667,\"regressLen\":258.0,\"regressDur\":0.0,\"pupilDiamMax\":0.0874,\"pupilDiamLag\":0.0859,\"timePrtctg\":0.0431,\"titleNo\":4.0,\"wordNo\":8.0}",
          "output": "0",
          "metadata_fold": 0,
          "metadata_feature_names": [
            "lineNo",
            "assgNo",
            "prevFixDur",
            "firstfixDur",
            "firstPassFixDur",
            "nextFixDur",
            "firstSaccLen",
            "lastSaccLen",
            "prevFixPos",
            "landingPos",
            "leavingPos",
            "totalFixDur",
            "meanFixDur",
            "regressLen",
            "regressDur",
            "pupilDiamMax",
            "pupilDiamLag",
            "timePrtctg",
            "titleNo",
            "wordNo"
          ],
          "metadata_task_type": "binary_classification",
          "metadata_n_classes": 2,
          "metadata_source": "hf_inria-soda/tabular-benchmark_clf_num_eye_movements",
          "metadata_row_index": 2
        }
      ]
    },
    {
      "dataset": "credit",
      "examples": [
        {
          "input": "{\"RevolvingUtilizationOfUnsecuredLines\":0.0069995,\"age\":38.0,\"NumberOfTime30-59DaysPastDueNotWorse\":0.0,\"DebtRatio\":0.30215034,\"MonthlyIncome\":5440.0,\"NumberOfOpenCreditLinesAndLoans\":4.0,\"NumberOfTimes90DaysLate\":0.0,\"NumberRealEstateLoansOrLines\":1.0,\"NumberOfTime60-89DaysPastDueNotWorse\":0.0,\"NumberOfDependents\":3.0}",
          "output": "0",
          "metadata_fold": 3,
          "metadata_feature_names": [
            "RevolvingUtilizationOfUnsecuredLines",
            "age",
            "NumberOfTime30-59DaysPastDueNotWorse",
            "DebtRatio",
            "MonthlyIncome",
            "NumberOfOpenCreditLinesAndLoans",
            "NumberOfTimes90DaysLate",
            "NumberRealEstateLoansOrLines",
            "NumberOfTime60-89DaysPastDueNotWorse",
            "NumberOfDependents"
          ],
          "metadata_task_type": "binary_classification",
          "metadata_n_classes": 2,
          "metadata_source": "hf_inria-soda/tabular-benchmark_clf_num_credit",
          "metadata_row_index": 0
        },
        {
          "input": "{\"RevolvingUtilizationOfUnsecuredLines\":0.704591673,\"age\":63.0,\"NumberOfTime30-59DaysPastDueNotWorse\":0.0,\"DebtRatio\":0.47144107,\"MonthlyIncome\":8000.0,\"NumberOfOpenCreditLinesAndLoans\":9.0,\"NumberOfTimes90DaysLate\":0.0,\"NumberRealEstateLoansOrLines\":1.0,\"NumberOfTime60-89DaysPastDueNotWorse\":0.0,\"NumberOfDependents\":0.0}",
          "output": "0",
          "metadata_fold": 4,
          "metadata_feature_names": [
            "RevolvingUtilizationOfUnsecuredLines",
            "age",
            "NumberOfTime30-59DaysPastDueNotWorse",
            "DebtRatio",
            "MonthlyIncome",
            "NumberOfOpenCreditLinesAndLoans",
            "NumberOfTimes90DaysLate",
            "NumberRealEstateLoansOrLines",
            "NumberOfTime60-89DaysPastDueNotWorse",
            "NumberOfDependents"
          ],
          "metadata_task_type": "binary_classification",
          "metadata_n_classes": 2,
          "metadata_source": "hf_inria-soda/tabular-benchmark_clf_num_credit",
          "metadata_row_index": 1
        },
        {
          "input": "{\"RevolvingUtilizationOfUnsecuredLines\":0.06311272,\"age\":57.0,\"NumberOfTime30-59DaysPastDueNotWorse\":0.0,\"DebtRatio\":0.068586283,\"MonthlyIncome\":5000.0,\"NumberOfOpenCreditLinesAndLoans\":17.0,\"NumberOfTimes90DaysLate\":0.0,\"NumberRealEstateLoansOrLines\":0.0,\"NumberOfTime60-89DaysPastDueNotWorse\":0.0,\"NumberOfDependents\":0.0}",
          "output": "0",
          "metadata_fold": 4,
          "metadata_feature_names": [
            "RevolvingUtilizationOfUnsecuredLines",
            "age",
            "NumberOfTime30-59DaysPastDueNotWorse",
            "DebtRatio",
            "MonthlyIncome",
            "NumberOfOpenCreditLinesAndLoans",
            "NumberOfTimes90DaysLate",
            "NumberRealEstateLoansOrLines",
            "NumberOfTime60-89DaysPastDueNotWorse",
            "NumberOfDependents"
          ],
          "metadata_task_type": "binary_classification",
          "metadata_n_classes": 2,
          "metadata_source": "hf_inria-soda/tabular-benchmark_clf_num_credit",
          "metadata_row_index": 2
        }
      ]
    },
    {
      "dataset": "miniboone",
      "examples": [
        {
          "input": "{\"ParticleID_0\":6.71799,\"ParticleID_1\":2.28262,\"ParticleID_2\":78.5358,\"ParticleID_3\":0.31256,\"ParticleID_4\":0.00717703,\"ParticleID_5\":0.120071,\"ParticleID_6\":0.665227,\"ParticleID_7\":0.7822680000000001,\"ParticleID_8\":3.5468300000000004,\"ParticleID_9\":0.151076,\"ParticleID_10\":4.37502,\"ParticleID_11\":249.996,\"ParticleID_12\":0.895834,\"ParticleID_13\":0.1555359999999999,\"ParticleID_14\":1.6784599999999998,\"ParticleID_15\":560.605,\"ParticleID_16\":0.181207,\"ParticleID_17\":37.5293,\"ParticleID_18\":0.311005,\"ParticleID_19\":0.55352,\"ParticleID_20\":-0.291338,\"ParticleID_21\":0.270335,\"ParticleID_22\":56.1874,\"ParticleID_23\":3.3048800000000003,\"ParticleID_24\":0.3189,\"ParticleID_25\":-0.25264,\"ParticleID_26\":131.184,\"ParticleID_27\":1.83014,\"ParticleID_28\":0.204757,\"ParticleID_29\":-0.574426,\"ParticleID_30\":10.689,\"ParticleID_31\":0.64061,\"ParticleID_32\":0.97622,\"ParticleID_33\":394.307,\"ParticleID_34\":0.0572286999999999,\"ParticleID_35\":0.235325,\"ParticleID_36\":-0.6753020000000001,\"ParticleID_37\":-2.97682,\"ParticleID_38\":1.53367,\"ParticleID_39\":0.0954721,\"ParticleID_40\":132.207,\"ParticleID_41\":-32.4068,\"ParticleID_42\":-0.1168309999999999,\"ParticleID_43\":4.87694,\"ParticleID_44\":0.0,\"ParticleID_45\":0.206118,\"ParticleID_46\":0.377589,\"ParticleID_47\":3.03752,\"ParticleID_48\":4.5865800000000005,\"ParticleID_49\":0.189042}",
          "output": "0",
          "metadata_fold": 0,
          "metadata_feature_names": [
            "ParticleID_0",
            "ParticleID_1",
            "ParticleID_2",
            "ParticleID_3",
            "ParticleID_4",
            "ParticleID_5",
            "ParticleID_6",
            "ParticleID_7",
            "ParticleID_8",
            "ParticleID_9",
            "ParticleID_10",
            "ParticleID_11",
            "ParticleID_12",
            "ParticleID_13",
            "ParticleID_14",
            "ParticleID_15",
            "ParticleID_16",
            "ParticleID_17",
            "ParticleID_18",
            "ParticleID_19",
            "ParticleID_20",
            "ParticleID_21",
            "ParticleID_22",
            "ParticleID_23",
            "ParticleID_24",
            "ParticleID_25",
            "ParticleID_26",
            "ParticleID_27",
            "ParticleID_28",
            "ParticleID_29",
            "ParticleID_30",
            "ParticleID_31",
            "ParticleID_32",
            "ParticleID_33",
            "ParticleID_34",
            "ParticleID_35",
            "ParticleID_36",
            "ParticleID_37",
            "ParticleID_38",
            "ParticleID_39",
            "ParticleID_40",
            "ParticleID_41",
            "ParticleID_42",
            "ParticleID_43",
            "ParticleID_44",
            "ParticleID_45",
            "ParticleID_46",
            "ParticleID_47",
            "ParticleID_48",
            "ParticleID_49"
          ],
          "metadata_task_type": "binary_classification",
          "metadata_n_classes": 2,
          "metadata_source": "hf_inria-soda/tabular-benchmark_clf_num_MiniBooNE",
          "metadata_row_index": 0
        },
        {
          "input": "{\"ParticleID_0\":6.283919999999999,\"ParticleID_1\":1.72557,\"ParticleID_2\":142.295,\"ParticleID_3\":0.375384,\"ParticleID_4\":0.00188324,\"ParticleID_5\":0.14015,\"ParticleID_6\":0.519,\"ParticleID_7\":0.743477,\"ParticleID_8\":3.40398,\"ParticleID_9\":0.140466,\"ParticleID_10\":4.32677,\"ParticleID_11\":388.395,\"ParticleID_12\":0.0384535,\"ParticleID_13\":0.145342,\"ParticleID_14\":1.50359,\"ParticleID_15\":595.422,\"ParticleID_16\":0.190824,\"ParticleID_17\":68.308,\"ParticleID_18\":0.2335219999999999,\"ParticleID_19\":0.345249,\"ParticleID_20\":0.2000849999999999,\"ParticleID_21\":0.295669,\"ParticleID_22\":54.0612,\"ParticleID_23\":2.82539,\"ParticleID_24\":0.280509,\"ParticleID_25\":-0.364169,\"ParticleID_26\":140.234,\"ParticleID_27\":1.73174,\"ParticleID_28\":0.214562,\"ParticleID_29\":-0.429988,\"ParticleID_30\":10.5939,\"ParticleID_31\":0.867107,\"ParticleID_32\":1.59207,\"ParticleID_33\":175.364,\"ParticleID_34\":0.0249169999999999,\"ParticleID_35\":0.285796,\"ParticleID_36\":0.37356,\"ParticleID_37\":-2.26237,\"ParticleID_38\":1.13771,\"ParticleID_39\":0.1228869999999999,\"ParticleID_40\":172.873,\"ParticleID_41\":-78.0728,\"ParticleID_42\":-0.4293109999999999,\"ParticleID_43\":4.00818,\"ParticleID_44\":0.0,\"ParticleID_45\":0.277303,\"ParticleID_46\":0.0528733,\"ParticleID_47\":4.72848,\"ParticleID_48\":1.11028,\"ParticleID_49\":0.1995289999999999}",
          "output": "0",
          "metadata_fold": 2,
          "metadata_feature_names": [
            "ParticleID_0",
            "ParticleID_1",
            "ParticleID_2",
            "ParticleID_3",
            "ParticleID_4",
            "ParticleID_5",
            "ParticleID_6",
            "ParticleID_7",
            "ParticleID_8",
            "ParticleID_9",
            "ParticleID_10",
            "ParticleID_11",
            "ParticleID_12",
            "ParticleID_13",
            "ParticleID_14",
            "ParticleID_15",
            "ParticleID_16",
            "ParticleID_17",
            "ParticleID_18",
            "ParticleID_19",
            "ParticleID_20",
            "ParticleID_21",
            "ParticleID_22",
            "ParticleID_23",
            "ParticleID_24",
            "ParticleID_25",
            "ParticleID_26",
            "ParticleID_27",
            "ParticleID_28",
            "ParticleID_29",
            "ParticleID_30",
            "ParticleID_31",
            "ParticleID_32",
            "ParticleID_33",
            "ParticleID_34",
            "ParticleID_35",
            "ParticleID_36",
            "ParticleID_37",
            "ParticleID_38",
            "ParticleID_39",
            "ParticleID_40",
            "ParticleID_41",
            "ParticleID_42",
            "ParticleID_43",
            "ParticleID_44",
            "ParticleID_45",
            "ParticleID_46",
            "ParticleID_47",
            "ParticleID_48",
            "ParticleID_49"
          ],
          "metadata_task_type": "binary_classification",
          "metadata_n_classes": 2,
          "metadata_source": "hf_inria-soda/tabular-benchmark_clf_num_MiniBooNE",
          "metadata_row_index": 1
        },
        {
          "input": "{\"ParticleID_0\":3.5089,\"ParticleID_1\":0.563817,\"ParticleID_2\":88.3913,\"ParticleID_3\":0.24528,\"ParticleID_4\":0.00370828,\"ParticleID_5\":0.400041,\"ParticleID_6\":1.31039,\"ParticleID_7\":0.898106,\"ParticleID_8\":3.3713,\"ParticleID_9\":0.235107,\"ParticleID_10\":4.19948,\"ParticleID_11\":217.095,\"ParticleID_12\":0.90418,\"ParticleID_13\":0.1503519999999999,\"ParticleID_14\":2.34487,\"ParticleID_15\":1510.1,\"ParticleID_16\":1.06945,\"ParticleID_17\":26.0557,\"ParticleID_18\":0.309023,\"ParticleID_19\":0.95839,\"ParticleID_20\":1.32668,\"ParticleID_21\":0.351051,\"ParticleID_22\":145.489,\"ParticleID_23\":4.58512,\"ParticleID_24\":0.4926979999999999,\"ParticleID_25\":0.690979,\"ParticleID_26\":59.1511,\"ParticleID_27\":1.35821,\"ParticleID_28\":0.136299,\"ParticleID_29\":-0.351475,\"ParticleID_30\":5.3689800000000005,\"ParticleID_31\":1.4335,\"ParticleID_32\":0.4914439999999999,\"ParticleID_33\":344.866,\"ParticleID_34\":0.105054,\"ParticleID_35\":0.34965,\"ParticleID_36\":1.17929,\"ParticleID_37\":-4.01251,\"ParticleID_38\":1.18211,\"ParticleID_39\":0.0690221,\"ParticleID_40\":127.947,\"ParticleID_41\":-5.59805,\"ParticleID_42\":0.92523,\"ParticleID_43\":5.171530000000001,\"ParticleID_44\":0.0,\"ParticleID_45\":0.1097609999999999,\"ParticleID_46\":0.20794,\"ParticleID_47\":0.691036,\"ParticleID_48\":-0.201779,\"ParticleID_49\":0.294377}",
          "output": "0",
          "metadata_fold": 4,
          "metadata_feature_names": [
            "ParticleID_0",
            "ParticleID_1",
            "ParticleID_2",
            "ParticleID_3",
            "ParticleID_4",
            "ParticleID_5",
            "ParticleID_6",
            "ParticleID_7",
            "ParticleID_8",
            "ParticleID_9",
            "ParticleID_10",
            "ParticleID_11",
            "ParticleID_12",
            "ParticleID_13",
            "ParticleID_14",
            "ParticleID_15",
            "ParticleID_16",
            "ParticleID_17",
            "ParticleID_18",
            "ParticleID_19",
            "ParticleID_20",
            "ParticleID_21",
            "ParticleID_22",
            "ParticleID_23",
            "ParticleID_24",
            "ParticleID_25",
            "ParticleID_26",
            "ParticleID_27",
            "ParticleID_28",
            "ParticleID_29",
            "ParticleID_30",
            "ParticleID_31",
            "ParticleID_32",
            "ParticleID_33",
            "ParticleID_34",
            "ParticleID_35",
            "ParticleID_36",
            "ParticleID_37",
            "ParticleID_38",
            "ParticleID_39",
            "ParticleID_40",
            "ParticleID_41",
            "ParticleID_42",
            "ParticleID_43",
            "ParticleID_44",
            "ParticleID_45",
            "ParticleID_46",
            "ParticleID_47",
            "ParticleID_48",
            "ParticleID_49"
          ],
          "metadata_task_type": "binary_classification",
          "metadata_n_classes": 2,
          "metadata_source": "hf_inria-soda/tabular-benchmark_clf_num_MiniBooNE",
          "metadata_row_index": 2
        }
      ]
    }
  ]
}